.travis.yml
CHANGELOG.rst
LICENSE
MANIFEST.in
README.rst
setup.cfg
setup.py
tox.ini
qcache_client.egg-info/PKG-INFO
qcache_client.egg-info/SOURCES.txt
qcache_client.egg-info/dependency_links.txt
qcache_client.egg-info/not-zip-safe
qcache_client.egg-info/requires.txt
qcache_client.egg-info/top_level.txt
qclient/__init__.py
qclient/node_ring.py
tests/test_nodering.py
tests/test_qclient.py